ingestables/Dockerfile
ingestables/__init__.py
ingestables/xm_launch_local.py
ingestables/torch/README.md
ingestables/torch/__init__.py
ingestables/torch/main.py
ingestables/torch/tabular_foundation_lab.py
ingestables/torch/types.py
ingestables/torch/utils.py
ingestables/torch/config/__init__.py
ingestables/torch/config/basic_config.py
ingestables/torch/data/__init__.py
ingestables/torch/data/base.py
ingestables/torch/data/data_loaders.py
ingestables/torch/data/dummy_dataset.py
ingestables/torch/data/encoders.py
ingestables/torch/data/encoding.py
ingestables/torch/data/pipeline.py
ingestables/torch/data/preprocessing.py
ingestables/torch/data/preprocessors.py
ingestables/torch/data/scenario_generators.py
ingestables/torch/data/serialization.py
ingestables/torch/data/utils.py
ingestables/torch/model/__init__.py
ingestables/torch/model/aligner.py
ingestables/torch/model/head.py
ingestables/torch/model/ingestables.py
ingestables/torch/model/interface.py
ingestables/torch/model/kv_combiner.py
ingestables/torch/model/sklearn_model.py
ingestables/torch/model/text_encoders.py
ingestables/torch/model/backbones/__init__.py
ingestables/torch/model/backbones/ft_transformer.py
ingestables/torch/model/backbones/t5_transformer.py
ingestables/torch/model/backbones/transtab_transformer.py
ingestables/torch/model/backbones/vanilla_transformer.py
ingestables/torch/model/lib/__init__.py
ingestables/torch/model/lib/activations.py
ingestables/torch/model/lib/categorical_embeddings.py
ingestables/torch/model/lib/deep.py
ingestables/torch/model/lib/generic_embeddings.py
ingestables/torch/model/lib/masking.py
ingestables/torch/model/lib/numerical_embeddings.py
ingestables/torch/model/lib/utils.py
ingestables/torch/train/__init__.py
ingestables/torch/train/lr_scheduler.py
ingestables/torch/train/metrics.py
ingestables/torch/train/train.py
ingestables/torch/train/train_deep.py
ingestables/torch/train/train_sklearn.py
ingestables-0.1.0.dist-info/licenses/LICENSE
ingestables-0.1.0.dist-info/WHEEL
ingestables-0.1.0.dist-info/METADATA
ingestables-0.1.0.dist-info/RECORD
